youtube_selenium_cookie/__init__.py
youtube_selenium_cookie/enums.py
youtube_selenium_cookie/exception.py
youtube_selenium_cookie/logs.py
youtube_selenium_cookie/upload.py
youtube_selenium_cookie/utils.py
youtube_cookie_uploader-0.5.1.dist-info/METADATA
youtube_cookie_uploader-0.5.1.dist-info/WHEEL
youtube_cookie_uploader-0.5.1.dist-info/top_level.txt
youtube_cookie_uploader-0.5.1.dist-info/RECORD
