Metadata-Version: 2.1
Name: youtube-cookie-uploader
Version: 0.5.1
Summary: A Youtube 3rd Party Library that uses selenium and webdriver_manager
Home-page: https://github.com/dataslid/youtube-cookie-uploader
Author: Abdulazeez Olabode
Author-email: dataslid@gmail.com
Requires-Dist: selenium
Requires-Dist: webdriver-manager
